open_observe_tracking_django/__init__.py
open_observe_tracking_django/log_to_open_observe.py
open_observe_tracking_django/logged_classes.py
open_observe_tracking_django/middleware.py
open_observe_tracking_django/open_observe_config.py
open_observe_tracking_django/open_observe_sender.py
open_observe_tracking_django/sender_creator.py
open_observe_tracking_django-0.2.2.dist-info/METADATA
open_observe_tracking_django-0.2.2.dist-info/WHEEL
open_observe_tracking_django-0.2.2.dist-info/top_level.txt
open_observe_tracking_django-0.2.2.dist-info/RECORD
